flink_gateway_api/__init__.py
flink_gateway_api/api/__init__.py
flink_gateway_api/api/default/__init__.py
flink_gateway_api/api/default/cancel_operation.py
flink_gateway_api/api/default/close_operation.py
flink_gateway_api/api/default/close_session.py
flink_gateway_api/api/default/complete_statement.py
flink_gateway_api/api/default/configure_session.py
flink_gateway_api/api/default/execute_statement.py
flink_gateway_api/api/default/fetch_results.py
flink_gateway_api/api/default/get_api_version.py
flink_gateway_api/api/default/get_info.py
flink_gateway_api/api/default/get_operation_status.py
flink_gateway_api/api/default/get_session_config.py
flink_gateway_api/api/default/open_session.py
flink_gateway_api/api/default/refresh_materialized_table.py
flink_gateway_api/api/default/trigger_session.py
flink_gateway_api/client.py
flink_gateway_api/errors.py
flink_gateway_api/models/__init__.py
flink_gateway_api/models/close_session_response_body.py
flink_gateway_api/models/column.py
flink_gateway_api/models/column_info.py
flink_gateway_api/models/complete_statement_request_body.py
flink_gateway_api/models/complete_statement_response_body.py
flink_gateway_api/models/configure_session_request_body.py
flink_gateway_api/models/constraint_type.py
flink_gateway_api/models/data_type.py
flink_gateway_api/models/execute_statement_request_body.py
flink_gateway_api/models/execute_statement_request_body_execution_config.py
flink_gateway_api/models/execute_statement_response_body.py
flink_gateway_api/models/expression.py
flink_gateway_api/models/fetch_results_response_body.py
flink_gateway_api/models/field_getter.py
flink_gateway_api/models/get_api_version_response_body.py
flink_gateway_api/models/get_info_response_body.py
flink_gateway_api/models/get_session_config_response_body.py
flink_gateway_api/models/get_session_config_response_body_properties.py
flink_gateway_api/models/logical_type.py
flink_gateway_api/models/logical_type_root.py
flink_sql_gateway_api-2.1.0.dist-info/LICENSE
flink_sql_gateway_api-2.1.0.dist-info/METADATA
flink_sql_gateway_api-2.1.0.dist-info/WHEEL
flink_sql_gateway_api-2.1.0.dist-info/RECORD
