Metadata-Version: 2.3
Name: flink-sql-gateway-api
Version: 2.1.0
Summary: A client library for accessing Flink SQL Gateway REST API
License: Apache-2.0
Keywords: Flink SQL Gateway,Python,Asyc Client
Author: Shijing Lu
Author-email: shijing.lu@gmail.com
Requires-Python: >=3.9,<4.0
Classifier: License :: OSI Approved :: Apache Software License
Classifier: Programming Language :: Python :: 3
Classifier: Programming Language :: Python :: 3.9
Classifier: Programming Language :: Python :: 3.10
Classifier: Programming Language :: Python :: 3.11
Classifier: Programming Language :: Python :: 3.12
Classifier: Programming Language :: Python :: 3.13
Requires-Dist: attrs (>=21.3.0)
Requires-Dist: httpx (>=0.20.0)
Requires-Dist: python-dateutil (>=2.8.0,<3.0.0)
Project-URL: Repository, https://github.com/resink-ai/flink-sql-gateway-api
